<annotation>
	<folder>hrosci</folder>
	<filename>hrosc 32.jpg</filename>
	<path>C:\Users\Edvard\venv\Slike\downloads\hrosci\hrosc 32.jpg</path>
	<source>
		<database>Unknown</database>
	</source>
	<size>
		<width>800</width>
		<height>600</height>
		<depth>3</depth>
	</size>
	<segmented>0</segmented>
	<object>
		<name>hrosc</name>
		<pose>Unspecified</pose>
		<truncated>0</truncated>
		<difficult>0</difficult>
		<bndbox>
			<xmin>414</xmin>
			<ymin>46</ymin>
			<xmax>673</xmax>
			<ymax>326</ymax>
		</bndbox>
	</object>
</annotation>
